odoo8_addon_l10n_it_reverse_charge-8.0.2.0.1-nspkg.pth
odoo_addons/l10n_it_reverse_charge/README.rst
odoo_addons/l10n_it_reverse_charge/__init__.py
odoo_addons/l10n_it_reverse_charge/__openerp__.py
odoo_addons/l10n_it_reverse_charge/i18n/it.po
odoo_addons/l10n_it_reverse_charge/i18n/l10n_it_reverse_charge.pot
odoo_addons/l10n_it_reverse_charge/i18n/sl.po
odoo_addons/l10n_it_reverse_charge/models/__init__.py
odoo_addons/l10n_it_reverse_charge/models/account_fiscal_position.py
odoo_addons/l10n_it_reverse_charge/models/account_invoice.py
odoo_addons/l10n_it_reverse_charge/models/account_rc_type.py
odoo_addons/l10n_it_reverse_charge/security/ir.model.access.csv
odoo_addons/l10n_it_reverse_charge/static/description/exemple1_0.png
odoo_addons/l10n_it_reverse_charge/static/description/exemple1_1.png
odoo_addons/l10n_it_reverse_charge/static/description/exemple1_2.png
odoo_addons/l10n_it_reverse_charge/static/description/exemple1_3.png
odoo_addons/l10n_it_reverse_charge/static/description/exemple1_4.png
odoo_addons/l10n_it_reverse_charge/static/description/exemple2_0.png
odoo_addons/l10n_it_reverse_charge/static/description/exemple2_1.png
odoo_addons/l10n_it_reverse_charge/static/description/exemple2_2.png
odoo_addons/l10n_it_reverse_charge/static/description/exemple2_3.png
odoo_addons/l10n_it_reverse_charge/static/description/exemple2_4.png
odoo_addons/l10n_it_reverse_charge/static/description/exemple3_0.png
odoo_addons/l10n_it_reverse_charge/static/description/exemple3_1.png
odoo_addons/l10n_it_reverse_charge/static/description/exemple3_2.png
odoo_addons/l10n_it_reverse_charge/static/description/exemple3_3.png
odoo_addons/l10n_it_reverse_charge/static/description/exemple3_4.png
odoo_addons/l10n_it_reverse_charge/static/description/exemple3_5.png
odoo_addons/l10n_it_reverse_charge/static/description/exemple3_6.png
odoo_addons/l10n_it_reverse_charge/static/description/fiscal_pos_intra.png
odoo_addons/l10n_it_reverse_charge/static/description/icon.png
odoo8_addon_l10n_it_reverse_charge-8.0.2.0.1.dist-info/METADATA
odoo8_addon_l10n_it_reverse_charge-8.0.2.0.1.dist-info/WHEEL
odoo8_addon_l10n_it_reverse_charge-8.0.2.0.1.dist-info/namespace_packages.txt
odoo8_addon_l10n_it_reverse_charge-8.0.2.0.1.dist-info/top_level.txt
odoo8_addon_l10n_it_reverse_charge-8.0.2.0.1.dist-info/RECORD
