Metadata-Version: 2.1
Name: odoo8-addon-l10n-it-reverse-charge
Version: 8.0.2.0.1
Summary: Reverse Charge for Italy
Home-page: https://www.odoo-italia.net
Author: Abstract, Agile Business Group,Odoo Community Association (OCA)
Author-email: support@odoo-community.org
License: AGPL-3
Platform: UNKNOWN
Classifier: Programming Language :: Python
Classifier: Framework :: Odoo
Classifier: License :: OSI Approved :: GNU Affero General Public License v3
Requires-Python: ~=2.7
Requires-Dist: odoo8-addon-account-invoice-entry-date
Requires-Dist: odoo (<9.0a,>=8.0a)
